README.rst
setup.py
clipboard_memo/__init__.py
clipboard_memo/direct.py
clipboard_memo/main.py
clipboard_memo.egg-info/PKG-INFO
clipboard_memo.egg-info/SOURCES.txt
clipboard_memo.egg-info/dependency_links.txt
clipboard_memo.egg-info/entry_points.txt
clipboard_memo.egg-info/requires.txt
clipboard_memo.egg-info/top_level.txt