Metadata-Version: 1.0
Name: clipboard-memo
Version: 0.2
Summary: A command-line clipboard manager
Home-page: http://github.com/arafsheikh/clipboard-memo
Author: Sheikh Araf
Author-email: arafsheikh@rocketmail.com
License: MIT
Keywords: clipboard memo manager command-line CLI
Platform: UNKNOWN
